fragment/__init__.py
fragment/__main__.py
fragment/project.py
fragment/registry.yaml
fragment/spatial.py
fragment/views.py
fragment/app/__init__.py
fragment/app/cli/__init__.py
fragment/app/cli/__main__.py
fragment/app/cli/calc.py
fragment/app/cli/cli.py
fragment/app/cli/hooks.py
fragment/app/cli/project.py
fragment/app/cli/strategy.py
fragment/app/cli/system.py
fragment/app/cli/util.py
fragment/backends/cp2k.py
fragment/core/PIETree.py
fragment/core/PIE_common.py
fragment/core/__init__.py
fragment/core/legacy_PIE.py
fragment/core/legacy_PIETree.py
fragment/core/logging.py
fragment/core/quickPIE.py
fragment/core/rPIETree.py
fragment/db/__init__.py
fragment/db/models.py
fragment/db/migrations/__init__.py
fragment/db/migrations/migration_20241017_160024.py
fragment/examples/__init__.py
fragment/examples/strategies/__init__.py
fragment/examples/strategies/distance.yaml
fragment/examples/strategies/example.yaml
fragment/examples/strategies/protein.yaml
fragment/examples/strategies/water6_test.yaml
fragment/examples/systems/6-benzene.xyz
fragment/examples/systems/Fw10.frag
fragment/examples/systems/MgOCH2.xyz
fragment/examples/systems/__init__.py
fragment/examples/systems/acetylene.xyz
fragment/examples/systems/benzene.xyz
fragment/examples/systems/ethane.xyz
fragment/examples/systems/ethanol.xyz
fragment/examples/systems/ethene.xyz
fragment/examples/systems/formaldehyde.xyz
fragment/examples/systems/many_benzenes.xyz
fragment/examples/systems/mg_complex.xyz
fragment/examples/systems/small_protien.pdb
fragment/examples/systems/tetrapeptide.pdb
fragment/examples/systems/two_AA.xyz
fragment/examples/systems/water6.frag
fragment/examples/systems/water6.xyz
fragment/fragmenting/__init__.py
fragment/fragmenting/abstract.py
fragment/fragmenting/covalent_components.py
fragment/fragmenting/groups.py
fragment/fragmenting/interaction_energy.py
fragment/fragmenting/water.py
fragment/mods/MIC.py
fragment/mods/__init__.py
fragment/mods/distance.py
fragment/mods/property_delta.py
fragment_qc-0.5.0.dist-info/LICENSE
fragment_qc-0.5.0.dist-info/METADATA
fragment_qc-0.5.0.dist-info/WHEEL
fragment_qc-0.5.0.dist-info/entry_points.txt
fragment_qc-0.5.0.dist-info/top_level.txt
fragment_qc-0.5.0.dist-info/RECORD
